[
  {
    "image_path": "/Users/chenyusu/flower-hackathon/first_images_dataset/train/2021.37_2022.07.25_first.JPG",
    "diagnosis": "The dental X-ray shows healthy tooth structure with good enamel density. No visible cavities or decay detected. Gum line appears normal.",
    "model_used": "manual",
    "status": "success"
  },
  {
    "image_path": "/Users/chenyusu/flower-hackathon/first_images_dataset/train/2023.37_2023.04.03_first.JPG",
    "diagnosis": "Minor tartar buildup observed on lower incisors. Recommend professional cleaning. Otherwise healthy dentition.",
    "model_used": "manual",
    "status": "success"
  },
  {
    "image_path": "/Users/chenyusu/flower-hackathon/first_images_dataset/train/2022.43_2022.07.13_first.JPG",
    "diagnosis": "Slight gum recession noted around upper molars. Monitor for progression. Good overall oral health maintained.",
    "model_used": "manual",
    "status": "success"
  }
]